at_connections.py
at_gps.py
at_send_at_command.py
bluetooth_connect.py
db_connect.py
db_get_records.py
db_input.py
db_setup.py
gpio.py
log_write_to_text_file.py
main.py
ping.py
rest_communicate.py
temp_mon.py
variables.py
pi_auto-0.9.1.dist-info/LICENSE
pi_auto-0.9.1.dist-info/METADATA
pi_auto-0.9.1.dist-info/WHEEL
pi_auto-0.9.1.dist-info/top_level.txt
pi_auto-0.9.1.dist-info/RECORD
